empire_platform_api_public_client/__init__.py
empire_platform_api_public_client/api_client.py
empire_platform_api_public_client/api_response.py
empire_platform_api_public_client/configuration.py
empire_platform_api_public_client/exceptions.py
empire_platform_api_public_client/py.typed
empire_platform_api_public_client/rest.py
empire_platform_api_public_client/api/__init__.py
empire_platform_api_public_client/api/allocated_auction_api.py
empire_platform_api_public_client/api/attachment_api.py
empire_platform_api_public_client/api/auction_api.py
empire_platform_api_public_client/api/audit_log_api.py
empire_platform_api_public_client/api/bidding_configuration_api.py
empire_platform_api_public_client/api/buy_now_offers_api.py
empire_platform_api_public_client/api/default_bid_api.py
empire_platform_api_public_client/api/default_nomination_api.py
empire_platform_api_public_client/api/finance_api.py
empire_platform_api_public_client/api/finance_information_api.py
empire_platform_api_public_client/api/manual_file_upload_api.py
empire_platform_api_public_client/api/messages_api.py
empire_platform_api_public_client/api/metadata_api.py
empire_platform_api_public_client/api/nomination_api.py
empire_platform_api_public_client/api/organisation_api.py
empire_platform_api_public_client/api/organisation_document_api.py
empire_platform_api_public_client/api/participant_dashboard_api.py
empire_platform_api_public_client/api/participant_overview_api.py
empire_platform_api_public_client/api/profile_api.py
empire_platform_api_public_client/api/public_allocated_auction_api.py
empire_platform_api_public_client/api/public_auction_api.py
empire_platform_api_public_client/api/public_nominations_api.py
empire_platform_api_public_client/api/reporting_api.py
empire_platform_api_public_client/api/secondary_market_api.py
empire_platform_api_public_client/api/transmission_right_api.py
empire_platform_api_public_client/api/user_api.py
empire_platform_api_public_client/models/__init__.py
empire_platform_api_public_client-7.1.0.dist-info/METADATA
empire_platform_api_public_client-7.1.0.dist-info/WHEEL
empire_platform_api_public_client-7.1.0.dist-info/top_level.txt
empire_platform_api_public_client-7.1.0.dist-info/RECORD
