Metadata-Version: 2.1
Name: empire-platform-api-public-client
Version: 7.1.0
Summary: Platform API
Home-page: 
Author: BritNed
Author-email: britned.info@britned.com
Keywords: OpenAPI,OpenAPI-Generator,Platform API
Requires-Dist: pydantic (>=2)
Requires-Dist: python-dateutil (>=2.8.2)
Requires-Dist: typing-extensions (>=4.7.1)
Requires-Dist: urllib3 (<3.0.0,>=1.25.3)
